mcsexps/1.py
mcsexps/2.py
mcsexps/3.py
mcsexps/4.py
mcsexps/5.py
mcsexps/6.py
mcsexps/7.py
mcsexps/__init__.py
mcsexps/__main__.py
mcsexps/setup.py
mcsexps-1.0.0.dist-info/METADATA
mcsexps-1.0.0.dist-info/WHEEL
mcsexps-1.0.0.dist-info/top_level.txt
mcsexps-1.0.0.dist-info/RECORD
