Metadata-Version: 2.1
Name: mcsexps
Version: 1.0.0
Classifier: Programming Language :: Python :: 3
Classifier: Programming Language :: Python :: 3.9
Classifier: Programming Language :: Python :: 3.10
Classifier: Programming Language :: Python :: 3.11
Requires-Dist: matplotlib
Requires-Dist: numpy
